LICENSE
MANIFEST.in
README.md
pyproject.toml
requirements.txt
setup.cfg
setup.py
tfvit/__init__.py
tfvit/ape.py
tfvit/clstok.py
tfvit/ls.py
tfvit/model.py
tfvit/swiglu.py
tfvit.egg-info/PKG-INFO
tfvit.egg-info/SOURCES.txt
tfvit.egg-info/dependency_links.txt
tfvit.egg-info/requires.txt
tfvit.egg-info/top_level.txt