Metadata-Version: 2.1
Name: tfvit
Version: 2.1.0
Summary: Keras v3 (all backends) reimplementation of ViT models.
Home-page: https://github.com/shkarupa-alex/tfvit
Author: Shkarupa Alex
Author-email: shkarupa.alex@gmail.com
License: MIT
Platform: UNKNOWN
Classifier: Development Status :: 5 - Production/Stable
Classifier: Intended Audience :: Developers
Classifier: Intended Audience :: Education
Classifier: Intended Audience :: Science/Research
Classifier: License :: OSI Approved :: MIT License
Classifier: Programming Language :: Python :: 3
Classifier: Topic :: Scientific/Engineering
Classifier: Topic :: Software Development
Classifier: Topic :: Software Development :: Libraries
Classifier: Topic :: Software Development :: Libraries :: Python Modules
License-File: LICENSE
